{
  "istilah": "i",
  "entri": "I varian: ientri varian: i",
  "bentukTidakBaku": "",
  "kataTurunan": [],
  "gabunganKata": [],
  "peribahasa": [],
  "etimologi": {
    "bahasaAsal": "",
    "arti": "",
    "kataAsal": ""
  },
  "data": [
    {
      "lema": "I varian: ientri varian: i",
      "arti": [
        {
          "kelas_kata": "n[Nomina: kata benda]",
          "deskripsi": "huruf ke-9 abjad Indonesia"
        },
        {
          "kelas_kata": "n[Nomina: kata benda]",
          "deskripsi": "nama huruf i"
        },
        {
          "kelas_kata": "n[Nomina: kata benda]",
          "deskripsi": "lambang bilangan I (dengan huruf kapital) angka Romawi"
        }
      ]
    },
    {
      "lema": "-i1 varian: -iah, -wi, -wiah, -nientri varian: -iah, -wi, -wiah, -ni",
      "arti": [
        {
          "kelas_kata": "sufiks[- : -]",
          "deskripsi": "berkenaan dengan; berdasar pada: alami; alamiah; badani; badaniah; duniawi; duniawiah; surgawi; gerejani"
        }
      ]
    },
    {
      "lema": "-i2",
      "arti": [
        {
          "kelas_kata": "sufiks[- : -]",
          "deskripsi": "memberikan: sampuli; selimuti; pagari"
        },
        {
          "kelas_kata": "sufiks[- : -]",
          "deskripsi": "berulang-ulang: lempari; pukuli; sirami"
        }
      ]
    }
  ]
}