{
  "istilah": "indo",
  "entri": "in.do",
  "bentukTidakBaku": "",
  "kataTurunan": [],
  "gabunganKata": [],
  "peribahasa": [],
  "etimologi": {
    "bahasaAsal": "",
    "arti": "",
    "kataAsal": ""
  },
  "data": [
    {
      "lema": "in.do",
      "arti": [
        {
          "kelas_kata": "n[Nomina: kata benda]",
          "deskripsi": "peranakan Eropa dengan Indonesia"
        },
        {
          "kelas_kata": "n[Nomina: kata benda] kp[kependekan]",
          "deskripsi": "Indonesia"
        }
      ]
    }
  ]
}