{
  "istilah": "inseminasi buatan",
  "entri": "inseminasi » inseminasi buatan",
  "bentukTidakBaku": "",
  "kataTurunan": [],
  "gabunganKata": [],
  "peribahasa": [],
  "etimologi": {
    "bahasaAsal": "",
    "arti": "",
    "kataAsal": ""
  },
  "data": [
    {
      "lema": "inseminasi » inseminasi buatan",
      "arti": [
        {
          "kelas_kata": "Zool[Zoologi: -]",
          "deskripsi": "penempatan sperma ke dalam uterus atau kandung telur yang dilakukan dengan bantuan manusia"
        }
      ]
    }
  ]
}