{
  "istilah": "instruktur",
  "entri": "in.struk.tur",
  "bentukTidakBaku": "",
  "kataTurunan": [],
  "gabunganKata": [],
  "peribahasa": [],
  "etimologi": {
    "bahasaAsal": "",
    "arti": "",
    "kataAsal": ""
  },
  "data": [
    {
      "lema": "in.struk.tur",
      "arti": [
        {
          "kelas_kata": "n[Nomina: kata benda]",
          "deskripsi": "orang yang bertugas mengajarkan sesuatu dan sekaligus memberikan latihan dan bimbingannya; pengajar; pelatih; pengasuh: seorang guru sangat diperlukan untuk menjadi -- di pusat pendidikan pertukangan itu"
        }
      ]
    }
  ]
}