{
  "istilah": "harian",
  "entri": "hari » ha.ri.an",
  "bentukTidakBaku": "",
  "kataTurunan": [],
  "gabunganKata": [],
  "peribahasa": [],
  "etimologi": {
    "bahasaAsal": "",
    "arti": "",
    "kataAsal": ""
  },
  "data": [
    {
      "lema": "hari » ha.ri.an",
      "arti": [
        {
          "kelas_kata": "n[Nomina: kata benda]",
          "deskripsi": "setiap hari: di pabrik itu ia dibayar ~"
        },
        {
          "kelas_kata": "n[Nomina: kata benda]",
          "deskripsi": "surat kabar atau koran yang terbit tiap hari"
        }
      ]
    }
  ]
}