{
  "istilah": "higrometer",
  "entri": "hig.ro.me.ter /higrometêr/",
  "bentukTidakBaku": "",
  "kataTurunan": [],
  "gabunganKata": [
    "higrometer elektrik",
    "higrometer kimia",
    "higrometer listrik",
    "higrometer rambut",
    "higrometer serap",
    "higrometer titik embun",
    "higrometer titik ibun"
  ],
  "peribahasa": [],
  "etimologi": {
    "bahasaAsal": "",
    "arti": "",
    "kataAsal": ""
  },
  "data": [
    {
      "lema": "hig.ro.me.ter /higrometêr/",
      "arti": [
        {
          "kelas_kata": "n[Nomina: kata benda]",
          "deskripsi": "alat untuk mengukur kelembapan relatif uap di udara"
        }
      ]
    }
  ]
}