{
  "istilah": "hipoksia hipoksemik",
  "entri": "hipoksia » hipoksia hipoksemik",
  "bentukTidakBaku": "",
  "kataTurunan": [],
  "gabunganKata": [],
  "peribahasa": [],
  "etimologi": {
    "bahasaAsal": "",
    "arti": "",
    "kataAsal": ""
  },
  "data": [
    {
      "lema": "hipoksia » hipoksia hipoksemik",
      "arti": [
        {
          "kelas_kata": "Dok[Kedokteran dan Fisiologi: -]",
          "deskripsi": "hipoksia yang disebabkan oleh tekanan parsial oksigen dalam pembuluh darah arteri"
        }
      ]
    }
  ]
}