{
  "istilah": "homo faber",
  "entri": "Lampiran",
  "bentukTidakBaku": "",
  "kataTurunan": [],
  "gabunganKata": [],
  "peribahasa": [],
  "etimologi": {
    "bahasaAsal": "",
    "arti": "",
    "kataAsal": ""
  },
  "data": [
    {
      "lema": "Lampiran",
      "arti": [
        {
          "kelas_kata": "ukp[Ungkapan] Lt[Latin: -]",
          "deskripsi": "manusia yang tahu teknik"
        }
      ]
    },
    {
      "lema": "homo faber",
      "arti": [
        {
          "kelas_kata": "[Ungkapan] [Latin: -]",
          "deskripsi": "manusia yang tahu teknik"
        }
      ]
    }
  ]
}