{
  "istilah": "cengking-mengking",
  "entri": "mengking » ceng.king-meng.king",
  "bentukTidakBaku": "",
  "kataTurunan": [],
  "gabunganKata": [],
  "peribahasa": [],
  "etimologi": {
    "bahasaAsal": "",
    "arti": "",
    "kataAsal": ""
  },
  "data": [
    {
      "lema": "mengking » ceng.king-meng.king",
      "arti": [
        {
          "kelas_kata": "v[Verba: kata kerja]",
          "deskripsi": "menjerit-jerit dengan suara melengking (karena ketakutan dan sebagainya)"
        }
      ]
    }
  ]
}