{
  "istilah": "cungap",
  "entri": "cu.ngap bentuk tidak baku: cungak",
  "bentukTidakBaku": "cungak",
  "kataTurunan": [
    "cungap-cangip",
    "mencungap",
    "tercungap",
    "tercungap-cungap"
  ],
  "gabunganKata": [],
  "peribahasa": [],
  "etimologi": {
    "bahasaAsal": "",
    "arti": "",
    "kataAsal": ""
  },
  "data": [
    {
      "lema": "cu.ngap bentuk tidak baku: cungak",
      "arti": [
        {
          "kelas_kata": "v[Verba: kata kerja]",
          "deskripsi": "buka tutup (tentang mulut)"
        }
      ]
    }
  ]
}