{
  "istilah": "makulat",
  "entri": "ma.ku.lat",
  "bentukTidakBaku": "",
  "kataTurunan": [],
  "gabunganKata": [],
  "peribahasa": [],
  "etimologi": {
    "bahasaAsal": "Arab",
    "arti": "masuk akal",
    "kataAsal": "ma‘qūlāt"
  },
  "data": [
    {
      "lema": "ma.ku.lat",
      "arti": [
        {
          "kelas_kata": "n[Nomina: kata benda] Ar[Arab: -]",
          "deskripsi": "pengetahuan tentang sesuatu yang gaib berdasarkan akal budi (tidak langsung berdasarkan wahyu); metafisika"
        }
      ]
    }
  ]
}