{
  "istilah": "manajer pelatihan",
  "entri": "manajer » manajer pelatihan",
  "bentukTidakBaku": "",
  "kataTurunan": [],
  "gabunganKata": [],
  "peribahasa": [],
  "etimologi": {
    "bahasaAsal": "",
    "arti": "",
    "kataAsal": ""
  },
  "data": [
    {
      "lema": "manajer » manajer pelatihan",
      "arti": [
        {
          "kelas_kata": "",
          "deskripsi": "pejabat pimpinan dalam perusahaan atau organisasi yang bertanggung jawab secara umum atas perumusan, pengarahan, dan kebijakan pendidikan dan pelatihan"
        }
      ]
    }
  ]
}