{
  "istilah": "martil",
  "entri": "mar.til",
  "bentukTidakBaku": "",
  "kataTurunan": [
    "bermartil"
  ],
  "gabunganKata": [],
  "peribahasa": [],
  "etimologi": {
    "bahasaAsal": "",
    "arti": "",
    "kataAsal": ""
  },
  "data": [
    {
      "lema": "mar.til",
      "arti": [
        {
          "kelas_kata": "n[Nomina: kata benda]",
          "deskripsi": "pemukul dari besi (bertangkai besi atau kayu); palu"
        },
        {
          "kelas_kata": "n[Nomina: kata benda] Olr[Olahraga: -]",
          "deskripsi": "alat yang digunakan dalam olahraga lontar martil"
        }
      ]
    }
  ]
}