{
  "istilah": "memonitor",
  "entri": "monitor » me.mo.ni.tor",
  "bentukTidakBaku": "",
  "kataTurunan": [],
  "gabunganKata": [],
  "peribahasa": [],
  "etimologi": {
    "bahasaAsal": "",
    "arti": "",
    "kataAsal": ""
  },
  "data": [
    {
      "lema": "monitor » me.mo.ni.tor",
      "arti": [
        {
          "kelas_kata": "v[Verba: kata kerja]",
          "deskripsi": "mengawasi, mengamati, atau mengecek dengan cermat, terutama untuk tujuan khusus; memantau"
        },
        {
          "kelas_kata": "v[Verba: kata kerja]",
          "deskripsi": "mengatur atau mengontrol kerja suatu mesin dan sebagainya"
        },
        {
          "kelas_kata": "v[Verba: kata kerja]",
          "deskripsi": "mengecek atau mengatur volume bunyi atau suara dalam merekam"
        }
      ]
    }
  ]
}