{
  "istilah": "menara derek",
  "entri": "menara » menara derek",
  "bentukTidakBaku": "",
  "kataTurunan": [],
  "gabunganKata": [],
  "peribahasa": [],
  "etimologi": {
    "bahasaAsal": "",
    "arti": "",
    "kataAsal": ""
  },
  "data": [
    {
      "lema": "menara » menara derek",
      "arti": [
        {
          "kelas_kata": "",
          "deskripsi": "derek yang digunakan di lokasi konstruksi, biasanya berlengan mendatar terpasang pada puncak menara"
        }
      ]
    }
  ]
}