{
  "istilah": "mengikutsertakan",
  "entri": "ikut serta » meng.i.kut.ser.ta.kan",
  "bentukTidakBaku": "",
  "kataTurunan": [],
  "gabunganKata": [],
  "peribahasa": [],
  "etimologi": {
    "bahasaAsal": "",
    "arti": "",
    "kataAsal": ""
  },
  "data": [
    {
      "lema": "ikut serta » meng.i.kut.ser.ta.kan",
      "arti": [
        {
          "kelas_kata": "v[Verba: kata kerja]",
          "deskripsi": "menjadikan agar turut berbuat sesuatu secara bersama: pelayanan kesehatan masyarakat ~ semua rumah sakit, baik negeri maupun swasta"
        }
      ]
    }
  ]
}