{
  "istilah": "mengingari",
  "entri": "ingar » meng.i.ngar.i",
  "bentukTidakBaku": "",
  "kataTurunan": [],
  "gabunganKata": [],
  "peribahasa": [],
  "etimologi": {
    "bahasaAsal": "",
    "arti": "",
    "kataAsal": ""
  },
  "data": [
    {
      "lema": "ingar » meng.i.ngar.i",
      "arti": [
        {
          "kelas_kata": "v[Verba: kata kerja]",
          "deskripsi": "mengganggu dengan membuat bising (hiruk-pikuk dan sebagainya): jangan ~ orang tidur"
        }
      ]
    }
  ]
}