{
  "istilah": "mengimbang",
  "entri": "imbang2 » meng.im.bang",
  "bentukTidakBaku": "",
  "kataTurunan": [],
  "gabunganKata": [],
  "peribahasa": [],
  "etimologi": {
    "bahasaAsal": "",
    "arti": "",
    "kataAsal": ""
  },
  "data": [
    {
      "lema": "imbang2 » meng.im.bang",
      "arti": [
        {
          "kelas_kata": "v[Verba: kata kerja]",
          "deskripsi": "menolak (tentang permintaan): sukar ~ permintaan tetangga yang sudah seperti saudara sendiri"
        }
      ]
    }
  ]
}