{
  "istilah": "meniatkan",
  "entri": "niat » me.ni.at.kan",
  "bentukTidakBaku": "",
  "kataTurunan": [],
  "gabunganKata": [],
  "peribahasa": [],
  "etimologi": {
    "bahasaAsal": "",
    "arti": "",
    "kataAsal": ""
  },
  "data": [
    {
      "lema": "niat » me.ni.at.kan",
      "arti": [
        {
          "kelas_kata": "v[Verba: kata kerja]",
          "deskripsi": "melakukan sesuatu dengan niat (memaksudkan): sejak dahulu saya memang sudah ~ semua itu"
        },
        {
          "kelas_kata": "v[Verba: kata kerja]",
          "deskripsi": "menazarkan; mengaulkan: dia sudah ~ kalau anaknya sembuh, akan memotong kambing"
        },
        {
          "kelas_kata": "v[Verba: kata kerja] Mk[Minangkabau: -]",
          "deskripsi": "mendoakan; mengharapkan"
        }
      ]
    }
  ]
}