{
  "istilah": "menyingsing",
  "entri": "singsing » me.nying.sing",
  "bentukTidakBaku": "",
  "kataTurunan": [],
  "gabunganKata": [],
  "peribahasa": [],
  "etimologi": {
    "bahasaAsal": "",
    "arti": "",
    "kataAsal": ""
  },
  "data": [
    {
      "lema": "singsing » me.nying.sing",
      "arti": [
        {
          "kelas_kata": "v[Verba: kata kerja]",
          "deskripsi": "menggulung (tentang lengan baju)"
        },
        {
          "kelas_kata": "v[Verba: kata kerja]",
          "deskripsi": "menyisih; lenyap (tentang awan, kabut, dan sebagainya): kabut pun ~"
        },
        {
          "kelas_kata": "v[Verba: kata kerja] ki[kiasan]",
          "deskripsi": "mulai terang; terbit (tentang fajar): semua persiapan penguburan dimulai ketika fajar ~"
        }
      ]
    }
  ]
}