{
  "istilah": "merayakan",
  "entri": "raya1 » me.ra.ya.kan",
  "bentukTidakBaku": "",
  "kataTurunan": [],
  "gabunganKata": [],
  "peribahasa": [],
  "etimologi": {
    "bahasaAsal": "",
    "arti": "",
    "kataAsal": ""
  },
  "data": [
    {
      "lema": "raya1 » me.ra.ya.kan",
      "arti": [
        {
          "kelas_kata": "v[Verba: kata kerja]",
          "deskripsi": "memuliakan (memperingati, memestakan) hari raya (peristiwa penting): ~ Hari Proklamasi Kemerdekaan Republik Indonesia; ~ hari lahir"
        }
      ]
    }
  ]
}