{
  "istilah": "minyak tung",
  "entri": "minyak » minyak tung",
  "bentukTidakBaku": "",
  "kataTurunan": [],
  "gabunganKata": [],
  "peribahasa": [],
  "etimologi": {
    "bahasaAsal": "",
    "arti": "",
    "kataAsal": ""
  },
  "data": [
    {
      "lema": "minyak » minyak tung",
      "arti": [
        {
          "kelas_kata": "",
          "deskripsi": "minyak nabati yang berasal dari biji buah pohon Aleurites cordata, dengan cara memeras biji tersebut, berwarna kuning muda, berbau tidak enak, digunakan dalam pembuatan cat, pernis, linoleum, dan pengering cat"
        }
      ]
    }
  ]
}