{
  "istilah": "muka",
  "entri": "mu.ka",
  "bentukTidakBaku": "",
  "kataTurunan": [
    "bermuka",
    "bermuka-muka",
    "berpermukaan",
    "bersemuka",
    "mengemuka",
    "mengemukakan",
    "menyemukakan",
    "muka-muka",
    "pemuka",
    "pengemuka",
    "pengemukaan",
    "permukaan",
    "semuka",
    "terkemuka"
  ],
  "gabunganKata": [
    "muka air tanah",
    "muka badak",
    "muka bantal",
    "muka berbakat",
    "muka berkilat",
    "muka datar",
    "muka fron",
    "muka kain",
    "muka kecut",
    "muka manis",
    "muka masam",
    "muka papan",
    "muka sabak",
    "muka stik",
    "muka tebal",
    "muka tembem"
  ],
  "peribahasa": [
    "bertemu muka dengan tedung; bertemu muka dengan tedung; bertemu muka dengan tedung; bintang di langit boleh dibilang, tetapi arang di muka tak sadar; buruk muka, cermin dibelah; buruk muka, cermin dibelah; buruk muka, cermin dibelah; datang tampak muka, pulang tampak punggung; datang tampak muka, pulang tampak punggung; di muka (di puncak) hidung; meludah ke langit, muka juga yang basah; menconteng arang di muka; menghapus(kan) arang di muka; muka bagai ditampar dengan kulit babi; muka licin, ekor berkedal; potong hidung, rusak muka; potong hidung, rusak muka; sedepa jalan ke muka, setelempap jalan ke belakang; talam dua muka; tarik muka dua belas; terconteng arang di muka; tercoreng arang di dahi (kening, muka); terpecak peluh di muka"
  ],
  "etimologi": {
    "bahasaAsal": "Sanskerta",
    "arti": "mulut, wajah, rupa, paras, depan, segi, atas, puncak, kepala",
    "kataAsal": "mukha"
  },
  "data": [
    {
      "lema": "mu.ka",
      "arti": [
        {
          "kelas_kata": "n[Nomina: kata benda]",
          "deskripsi": "bagian depan kepala, dari dahi atas sampai ke dagu dan antara telinga yang satu dan telinga yang lain: setiap pagi ia membasuh --nya dengan air hangat"
        },
        {
          "kelas_kata": "n[Nomina: kata benda]",
          "deskripsi": "wajah; air muka; rupa muka: disambut dengan -- manis"
        },
        {
          "kelas_kata": "n[Nomina: kata benda]",
          "deskripsi": "orang: pada malam itu kita dikenalkan dengan beberapa -- baru"
        },
        {
          "kelas_kata": "n[Nomina: kata benda]",
          "deskripsi": "bagian luar sebelah depan; depan; hadapan: mereka menunggu kami di -- kantor"
        },
        {
          "kelas_kata": "n[Nomina: kata benda]",
          "deskripsi": "sisi bagian (sebelah depan): bagian -- rumah itu dibuat bergaya Spanyol"
        },
        {
          "kelas_kata": "n[Nomina: kata benda]",
          "deskripsi": "halaman (buku); pagina: bagian yang kaucari itu terdapat dalam bukumu pada -- 10"
        },
        {
          "kelas_kata": "n[Nomina: kata benda]",
          "deskripsi": "bidang rata di atas suatu benda (air, laut, bumi, dan sebagainya); permukaan: segala yang ada di -- bumi"
        },
        {
          "kelas_kata": "n[Nomina: kata benda]",
          "deskripsi": "yang dahulu; yang terdahulu: di -- sudah saya uraikan tentang hal itu"
        },
        {
          "kelas_kata": "n[Nomina: kata benda]",
          "deskripsi": "yang akan datang: minggu --; mereka akan menikah pada bulan -- ini"
        }
      ]
    }
  ]
}