{
  "istilah": "dalang jemblung",
  "entri": "dalang » dalang jemblung",
  "bentukTidakBaku": "",
  "kataTurunan": [],
  "gabunganKata": [],
  "peribahasa": [],
  "etimologi": {
    "bahasaAsal": "",
    "arti": "",
    "kataAsal": ""
  },
  "data": [
    {
      "lema": "dalang » dalang jemblung",
      "arti": [
        {
          "kelas_kata": "Sen[Kesenian: -]",
          "deskripsi": "kesenian tradisi lisan rakyat Banyumas yang menampilkan cerita Ramayana, Mahabarata, terdiri atas empat atau lima pemain pria dan satu wanita yang berperan ganda sebagai pemusik mulut, penyanyi, pelaku, dan pencerita"
        }
      ]
    }
  ]
}