{
  "istilah": "dorongan sembur",
  "entri": "dorong » dorongan » dorongan sembur",
  "bentukTidakBaku": "",
  "kataTurunan": [],
  "gabunganKata": [],
  "peribahasa": [],
  "etimologi": {
    "bahasaAsal": "",
    "arti": "",
    "kataAsal": ""
  },
  "data": [
    {
      "lema": "dorong » dorongan » dorongan sembur",
      "arti": [
        {
          "kelas_kata": "Dirg[Kedirgantaraan: -]",
          "deskripsi": "sistem propulsi yang menggunakan aliran gas kecepatan tinggi sebagai pendorongnya"
        }
      ]
    }
  ]
}