{
  "istilah": "frekuensi ultratinggi",
  "entri": "frekuensi » frekuensi ultratinggi",
  "bentukTidakBaku": "",
  "kataTurunan": [],
  "gabunganKata": [],
  "peribahasa": [],
  "etimologi": {
    "bahasaAsal": "",
    "arti": "",
    "kataAsal": ""
  },
  "data": [
    {
      "lema": "frekuensi » frekuensi ultratinggi",
      "arti": [
        {
          "kelas_kata": "El[Elektronika: -]",
          "deskripsi": "frekuensi gelombang elektromagnetik antara 300—3000 MHz"
        }
      ]
    }
  ]
}