{
  "istilah": "keberlimpahan",
  "entri": "limpah » ke.ber.lim.pah.an",
  "bentukTidakBaku": "",
  "kataTurunan": [],
  "gabunganKata": [],
  "peribahasa": [],
  "etimologi": {
    "bahasaAsal": "",
    "arti": "",
    "kataAsal": ""
  },
  "data": [
    {
      "lema": "limpah » ke.ber.lim.pah.an",
      "arti": [
        {
          "kelas_kata": "n[Nomina: kata benda]",
          "deskripsi": "hal berlimpahan; keadaan berlimpahan: hidupnya selalu penuh ~ rezeki"
        }
      ]
    }
  ]
}