{
  "istilah": "kecemburuan",
  "entri": "cemburu » ke.cem.bu.ru.an",
  "bentukTidakBaku": "",
  "kataTurunan": [],
  "gabunganKata": [],
  "peribahasa": [],
  "etimologi": {
    "bahasaAsal": "",
    "arti": "",
    "kataAsal": ""
  },
  "data": [
    {
      "lema": "cemburu » ke.cem.bu.ru.an",
      "arti": [
        {
          "kelas_kata": "n[Nomina: kata benda]",
          "deskripsi": "keirihatian; kesirikan"
        },
        {
          "kelas_kata": "n[Nomina: kata benda]",
          "deskripsi": "kecurigaan; kekurangpercayaan"
        }
      ]
    }
  ]
}