{
  "istilah": "kelepek-kelepek",
  "entri": "ke.le.pek-ke.le.pek /kêlêpêk-kêlêpêk/",
  "bentukTidakBaku": "",
  "kataTurunan": [],
  "gabunganKata": [],
  "peribahasa": [],
  "etimologi": {
    "bahasaAsal": "",
    "arti": "",
    "kataAsal": ""
  },
  "data": [
    {
      "lema": "ke.le.pek-ke.le.pek /kêlêpêk-kêlêpêk/",
      "arti": [
        {
          "kelas_kata": "v[Verba: kata kerja] cak[Cakapan: menandai kata yang digunakan dalam ragam takbaku]",
          "deskripsi": "menggelepar-gelepar (seperti ayam yang sedang meregang nyawa, dan sebagainya): lipas itu -- setelah disemprot"
        },
        {
          "kelas_kata": "v[Verba: kata kerja] cak[Cakapan: menandai kata yang digunakan dalam ragam takbaku] ki[kiasan] ki[kiasan]",
          "deskripsi": "sangat terpesona (terpikat) sehingga tidak berdaya: hatiku -- saat pertama kali melihatnya"
        }
      ]
    }
  ]
}