{
  "istilah": "ketentuan",
  "entri": "tentu » ke.ten.tu.an",
  "bentukTidakBaku": "",
  "kataTurunan": [],
  "gabunganKata": [
    "ketentuan hukum",
    "ketentuan memukul",
    "ketentuan tambahan"
  ],
  "peribahasa": [],
  "etimologi": {
    "bahasaAsal": "",
    "arti": "",
    "kataAsal": ""
  },
  "data": [
    {
      "lema": "tentu » ke.ten.tu.an",
      "arti": [
        {
          "kelas_kata": "n[Nomina: kata benda]",
          "deskripsi": "sesuatu yang sudah tentu atau yang telah ditentukan; ketetapan: setelah ujian, kini kita tinggal menantikan ~ nasib saja; ~ yang lama masih tetap berlaku"
        },
        {
          "kelas_kata": "n[Nomina: kata benda]",
          "deskripsi": "kepastian: dengan adanya ~ itu setiap pegawai boleh melakukan kerja tambahan"
        }
      ]
    }
  ]
}