{
  "istilah": "kontrak kontingensi",
  "entri": "kontrak » kontrak kontingensi",
  "bentukTidakBaku": "",
  "kataTurunan": [],
  "gabunganKata": [],
  "peribahasa": [],
  "etimologi": {
    "bahasaAsal": "",
    "arti": "",
    "kataAsal": ""
  },
  "data": [
    {
      "lema": "kontrak » kontrak kontingensi",
      "arti": [
        {
          "kelas_kata": "Psi[Psikologi: -]",
          "deskripsi": "prosedur perilaku yang harus dilakukan untuk menentukan kondisi selanjutnya, biasanya digunakan untuk anak-anak"
        }
      ]
    }
  ]
}