{
  "istilah": "kredit dagang",
  "entri": "kredit1 » kredit dagang",
  "bentukTidakBaku": "",
  "kataTurunan": [],
  "gabunganKata": [],
  "peribahasa": [],
  "etimologi": {
    "bahasaAsal": "",
    "arti": "",
    "kataAsal": ""
  },
  "data": [
    {
      "lema": "kredit1 » kredit dagang",
      "arti": [
        {
          "kelas_kata": "Ek[Ekonomi dan Keuangan: -]",
          "deskripsi": "kredit yang diberikan oleh perusahaan dagang kepada perusahaan dagang lain"
        }
      ]
    }
  ]
}