{
  "istilah": "teramisin",
  "entri": "te.ra.mi.sin",
  "bentukTidakBaku": "",
  "kataTurunan": [],
  "gabunganKata": [],
  "peribahasa": [],
  "etimologi": {
    "bahasaAsal": "",
    "arti": "",
    "kataAsal": ""
  },
  "data": [
    {
      "lema": "te.ra.mi.sin",
      "arti": [
        {
          "kelas_kata": "n[Nomina: kata benda] Dok[Kedokteran dan Fisiologi: -]",
          "deskripsi": "antibiotik yang digunakan sebagai penyembuh peradangan pada saluran pernapasan"
        }
      ]
    }
  ]
}