{
  "istilah": "termodern",
  "entri": "modern » ter.mo.dern",
  "bentukTidakBaku": "",
  "kataTurunan": [],
  "gabunganKata": [],
  "peribahasa": [],
  "etimologi": {
    "bahasaAsal": "",
    "arti": "",
    "kataAsal": ""
  },
  "data": [
    {
      "lema": "modern » ter.mo.dern",
      "arti": [
        {
          "kelas_kata": "a[Adjektiva: kata yang menjelaskan nomina atau pronomina]",
          "deskripsi": "paling modern: rumah sakit ini diperlengkapi dengan peralatan ~"
        }
      ]
    }
  ]
}