{
  "istilah": "transfer nol",
  "entri": "transfer » transfer nol",
  "bentukTidakBaku": "",
  "kataTurunan": [],
  "gabunganKata": [],
  "peribahasa": [],
  "etimologi": {
    "bahasaAsal": "",
    "arti": "",
    "kataAsal": ""
  },
  "data": [
    {
      "lema": "transfer » transfer nol",
      "arti": [
        {
          "kelas_kata": "Olr[Olahraga: -]",
          "deskripsi": "gerakan ketika keterampilan lain di masa lalu tidak berpengaruh terhadap keterampilan baru yang akan dipelajari"
        }
      ]
    }
  ]
}