{
  "istilah": "paronisia",
  "entri": "pa.ro.ni.si.a",
  "bentukTidakBaku": "",
  "kataTurunan": [],
  "gabunganKata": [],
  "peribahasa": [],
  "etimologi": {
    "bahasaAsal": "",
    "arti": "",
    "kataAsal": ""
  },
  "data": [
    {
      "lema": "pa.ro.ni.si.a",
      "arti": [
        {
          "kelas_kata": "n[Nomina: kata benda] Dok[Kedokteran dan Fisiologi: -]",
          "deskripsi": "infeksi yang disebabkan oleh jamur, kulit sekitar kuku menjadi merah dan bengkak, banyak terdapat pada wanita yang tangannya sering kena air dan detergen"
        }
      ]
    }
  ]
}