{
  "istilah": "patronimik",
  "entri": "pat.ro.ni.mik",
  "bentukTidakBaku": "",
  "kataTurunan": [],
  "gabunganKata": [],
  "peribahasa": [],
  "etimologi": {
    "bahasaAsal": "",
    "arti": "",
    "kataAsal": ""
  },
  "data": [
    {
      "lema": "pat.ro.ni.mik",
      "arti": [
        {
          "kelas_kata": "n[Nomina: kata benda]",
          "deskripsi": "nama seseorang yang diambil dari nama ayah kandung atau leluhur laki-laki dengan menambahkan awalan atau akhiran"
        }
      ]
    }
  ]
}