{
  "istilah": "pembilas",
  "entri": "bilas » pem.bi.las",
  "bentukTidakBaku": "",
  "kataTurunan": [],
  "gabunganKata": [],
  "peribahasa": [],
  "etimologi": {
    "bahasaAsal": "",
    "arti": "",
    "kataAsal": ""
  },
  "data": [
    {
      "lema": "bilas » pem.bi.las",
      "arti": [
        {
          "kelas_kata": "n[Nomina: kata benda]",
          "deskripsi": "air pencuci (pembasuh) yang kedua kali"
        },
        {
          "kelas_kata": "n[Nomina: kata benda]",
          "deskripsi": "alat konsentrasi yang digunakan untuk mengambil mineral berharga pada tahap akhir sehingga ampasnya merupakan ampas akhir untuk dibuang"
        }
      ]
    }
  ]
}