{
  "istilah": "pendaftaran",
  "entri": "daftar » pen.daf.tar.an",
  "bentukTidakBaku": "",
  "kataTurunan": [],
  "gabunganKata": [],
  "peribahasa": [],
  "etimologi": {
    "bahasaAsal": "",
    "arti": "",
    "kataAsal": ""
  },
  "data": [
    {
      "lema": "daftar » pen.daf.tar.an",
      "arti": [
        {
          "kelas_kata": "n[Nomina: kata benda]",
          "deskripsi": "proses, cara, perbuatan mendaftar (mendaftarkan); pencatatan nama, alamat, dan sebagainya dalam daftar"
        },
        {
          "kelas_kata": "n[Nomina: kata benda]",
          "deskripsi": "perihal mendaftar (mendaftarkan): ~ murid baru diadakan dalam bulan Desember"
        }
      ]
    }
  ]
}