{
  "istilah": "penghambat",
  "entri": "hambat1 » peng.ham.bat",
  "bentukTidakBaku": "",
  "kataTurunan": [],
  "gabunganKata": [
    "penghambat karbohidrat"
  ],
  "peribahasa": [],
  "etimologi": {
    "bahasaAsal": "",
    "arti": "",
    "kataAsal": ""
  },
  "data": [
    {
      "lema": "hambat1 » peng.ham.bat",
      "arti": [
        {
          "kelas_kata": "n[Nomina: kata benda]",
          "deskripsi": "orang yang menghambat: ia yang dituding sebagai ~ keberhasilan program ini"
        },
        {
          "kelas_kata": "n[Nomina: kata benda]",
          "deskripsi": "alat yang dipakai untuk menghambat"
        }
      ]
    }
  ]
}