{
  "istilah": "penisilinase",
  "entri": "pe.ni.si.li.na.se /penisilinasê/",
  "bentukTidakBaku": "",
  "kataTurunan": [],
  "gabunganKata": [],
  "peribahasa": [],
  "etimologi": {
    "bahasaAsal": "",
    "arti": "",
    "kataAsal": ""
  },
  "data": [
    {
      "lema": "pe.ni.si.li.na.se /penisilinasê/",
      "arti": [
        {
          "kelas_kata": "n[Nomina: kata benda] Bio[Biologi: -]",
          "deskripsi": "enzim yang menguraikan penisilin menjadi asam penisilinat yang tidak memiliki daya antibiotik lagi"
        }
      ]
    }
  ]
}