{
  "istilah": "protobintang",
  "entri": "pro.to.bin.tang",
  "bentukTidakBaku": "",
  "kataTurunan": [],
  "gabunganKata": [],
  "peribahasa": [],
  "etimologi": {
    "bahasaAsal": "",
    "arti": "",
    "kataAsal": ""
  },
  "data": [
    {
      "lema": "pro.to.bin.tang",
      "arti": [
        {
          "kelas_kata": "n[Nomina: kata benda] Astron[Astronomi: -]",
          "deskripsi": "pembentukan bintang pada tahap awal setelah terjadi proses kompresi gas pada awan molekul raksasa"
        }
      ]
    }
  ]
}