{
  "istilah": "abortif",
  "entri": "a.bor.tif",
  "bentukTidakBaku": "",
  "kataTurunan": [],
  "gabunganKata": [],
  "peribahasa": [],
  "etimologi": {
    "bahasaAsal": "",
    "arti": "",
    "kataAsal": ""
  },
  "data": [
    {
      "lema": "a.bor.tif",
      "arti": [
        {
          "kelas_kata": "a[Adjektiva: kata yang menjelaskan nomina atau pronomina] Dok[Kedokteran dan Fisiologi: -]",
          "deskripsi": "terhenti dalam perkembangan"
        },
        {
          "kelas_kata": "a[Adjektiva: kata yang menjelaskan nomina atau pronomina]",
          "deskripsi": "tidak sempurna"
        }
      ]
    }
  ]
}