{
  "istilah": "adenokarsinoma",
  "entri": "a.de.no.kar.si.no.ma",
  "bentukTidakBaku": "",
  "kataTurunan": [],
  "gabunganKata": [],
  "peribahasa": [],
  "etimologi": {
    "bahasaAsal": "",
    "arti": "",
    "kataAsal": ""
  },
  "data": [
    {
      "lema": "a.de.no.kar.si.no.ma",
      "arti": [
        {
          "kelas_kata": "n[Nomina: kata benda] Dok[Kedokteran dan Fisiologi: -]",
          "deskripsi": "karsinoma yang tumbuh dan berkembang pada organ tubuh yang memiliki kelenjar, seperti payudara, paru-paru, esofagus, kolon, pankreas, dan prostat"
        }
      ]
    }
  ]
}