{
  "istilah": "angkin",
  "entri": "ang.kin",
  "bentukTidakBaku": "",
  "kataTurunan": [],
  "gabunganKata": [],
  "peribahasa": [],
  "etimologi": {
    "bahasaAsal": "Hokkien dialek Zhangzhou",
    "arti": "ikat pinggang",
    "kataAsal": "âng kin"
  },
  "data": [
    {
      "lema": "ang.kin",
      "arti": [
        {
          "kelas_kata": "n[Nomina: kata benda]",
          "deskripsi": "ikat pinggang yang dibuat dari cita dan kain, biasanya dipakai oleh wanita"
        },
        {
          "kelas_kata": "n[Nomina: kata benda]",
          "deskripsi": "kain batik bermotif banji"
        }
      ]
    }
  ]
}