{
  "istilah": "atap rumbia (ijuk) perabung upih",
  "entri": "atap » atap rumbia (ijuk) perabung upih",
  "bentukTidakBaku": "",
  "kataTurunan": [],
  "gabunganKata": [],
  "peribahasa": [],
  "etimologi": {
    "bahasaAsal": "",
    "arti": "",
    "kataAsal": ""
  },
  "data": [
    {
      "lema": "atap » atap rumbia (ijuk) perabung upih",
      "arti": [
        {
          "kelas_kata": "",
          "deskripsi": "barang yang baik bercampur dengan barang yang buruk"
        }
      ]
    }
  ]
}