{
  "istilah": "ayak",
  "entri": "a.yak1",
  "bentukTidakBaku": "",
  "kataTurunan": [
    "ayakan",
    "mengayak",
    "pengayak",
    "pengayakan",
    "mengayak"
  ],
  "gabunganKata": [
    "ayakan tepung"
  ],
  "peribahasa": [],
  "etimologi": {
    "bahasaAsal": "",
    "arti": "",
    "kataAsal": ""
  },
  "data": [
    {
      "lema": "a.yak1",
      "arti": [
        {
          "kelas_kata": "",
          "deskripsi": "ayakan; mengayak; pengayak; pengayakan"
        }
      ]
    },
    {
      "lema": "a.yak2",
      "arti": [
        {
          "kelas_kata": "",
          "deskripsi": "mengayak"
        }
      ]
    }
  ]
}