{
  "istilah": "lemah saraf",
  "entri": "lemah1 » lemah saraf",
  "bentukTidakBaku": "",
  "kataTurunan": [],
  "gabunganKata": [],
  "peribahasa": [],
  "etimologi": {
    "bahasaAsal": "",
    "arti": "",
    "kataAsal": ""
  },
  "data": [
    {
      "lema": "lemah1 » lemah saraf",
      "arti": [
        {
          "kelas_kata": "",
          "deskripsi": "agak gila; agak terganggu pikirannya"
        },
        {
          "kelas_kata": "",
          "deskripsi": "mudah terkejut"
        }
      ]
    }
  ]
}