{
  "istilah": "lipas kudung",
  "entri": "lipas » lipas kudung",
  "bentukTidakBaku": "",
  "kataTurunan": [],
  "gabunganKata": [],
  "peribahasa": [],
  "etimologi": {
    "bahasaAsal": "",
    "arti": "",
    "kataAsal": ""
  },
  "data": [
    {
      "lema": "lipas » lipas kudung",
      "arti": [
        {
          "kelas_kata": "",
          "deskripsi": "kecoak berukuran besar yang bertubuh mengilap berwarna cokelat tua atau hitam, jantannya memiliki sayap panjang yang menutupi tiga perempat abdomen, hidup di daerah lembap, merupakan hama rumah di Amerika Serikat, dan dapat menyebarkan penyakit disentri, tifus, dan keracunan makanan〔Blatta orientalis〕"
        }
      ]
    }
  ]
}