{
  "istilah": "lumpur",
  "entri": "lum.pur",
  "bentukTidakBaku": "",
  "kataTurunan": [
    "berlumpur",
    "pelumpuran"
  ],
  "gabunganKata": [
    "lumpur aktif",
    "lumpur basa",
    "lumpur ketam",
    "lumpur vulkanik"
  ],
  "peribahasa": [
    "beroleh lumpur di tempat yang kering; seperti belut pulang ke lumpur; takut akan lumpur, lari ke duri"
  ],
  "etimologi": {
    "bahasaAsal": "",
    "arti": "",
    "kataAsal": ""
  },
  "data": [
    {
      "lema": "lum.pur",
      "arti": [
        {
          "kelas_kata": "n[Nomina: kata benda]",
          "deskripsi": "tanah lunak dan berair; tanah becek; luluk"
        }
      ]
    }
  ]
}