{
  "istilah": "saku gembung",
  "entri": "saku1 » saku gembung",
  "bentukTidakBaku": "",
  "kataTurunan": [],
  "gabunganKata": [],
  "peribahasa": [],
  "etimologi": {
    "bahasaAsal": "",
    "arti": "",
    "kataAsal": ""
  },
  "data": [
    {
      "lema": "saku1 » saku gembung",
      "arti": [
        {
          "kelas_kata": "",
          "deskripsi": "saku tempel yang tampak menggembung karena bagian bawah memiliki lipit, bagian sampingnya dapat ditarik"
        }
      ]
    }
  ]
}