{
  "istilah": "sekian",
  "entri": "kian1 » se.ki.an",
  "bentukTidakBaku": "",
  "kataTurunan": [],
  "gabunganKata": [],
  "peribahasa": [],
  "etimologi": {
    "bahasaAsal": "",
    "arti": "",
    "kataAsal": ""
  },
  "data": [
    {
      "lema": "kian1 » se.ki.an",
      "arti": [
        {
          "kelas_kata": "n[Nomina: kata benda]",
          "deskripsi": "sebanyak itu (ini); sampai sebegitu: ~lah uraian mengenai teori baru ini"
        }
      ]
    },
    {
      "lema": "se.ki.an /sêkian/",
      "arti": [
        {
          "kelas_kata": "",
          "deskripsi": "lihat kian1"
        }
      ]
    }
  ]
}