{
  "istilah": "selukat",
  "entri": "se.lu.kat /sêlukat/",
  "bentukTidakBaku": "",
  "kataTurunan": [
    "menyelukat"
  ],
  "gabunganKata": [],
  "peribahasa": [],
  "etimologi": {
    "bahasaAsal": "Jawa Kuno",
    "arti": "instrument tertentu, barangkali instrument perkusi seperti saron kecil",
    "kataAsal": "salukat"
  },
  "data": [
    {
      "lema": "se.lu.kat /sêlukat/",
      "arti": [
        {
          "kelas_kata": "n[Nomina: kata benda]",
          "deskripsi": "alat gamelan kuno sejenis saron kecil dengan bilah-bilah lebar"
        }
      ]
    }
  ]
}