{
  "istilah": "sesagon",
  "entri": "sagon » se.sa.gon",
  "bentukTidakBaku": "",
  "kataTurunan": [],
  "gabunganKata": [],
  "peribahasa": [],
  "etimologi": {
    "bahasaAsal": "",
    "arti": "",
    "kataAsal": ""
  },
  "data": [
    {
      "lema": "sagon » se.sa.gon",
      "arti": [
        {
          "kelas_kata": "n[Nomina: kata benda]",
          "deskripsi": "sagon"
        }
      ]
    },
    {
      "lema": "se.sa.gon /sêsagon/",
      "arti": [
        {
          "kelas_kata": "",
          "deskripsi": "lihat sagon"
        }
      ]
    }
  ]
}