{
  "istilah": "sorongan",
  "entri": "sorong » so.rong.an",
  "bentukTidakBaku": "",
  "kataTurunan": [],
  "gabunganKata": [],
  "peribahasa": [],
  "etimologi": {
    "bahasaAsal": "",
    "arti": "",
    "kataAsal": ""
  },
  "data": [
    {
      "lema": "sorong » so.rong.an",
      "arti": [
        {
          "kelas_kata": "n[Nomina: kata benda]",
          "deskripsi": "yang disorong(kan)"
        },
        {
          "kelas_kata": "n[Nomina: kata benda]",
          "deskripsi": "alat untuk menyorong"
        },
        {
          "kelas_kata": "n[Nomina: kata benda]",
          "deskripsi": "pemberian; hadiah; suapan"
        }
      ]
    }
  ]
}