{
  "istilah": "suara sumbang",
  "entri": "suara » suara sumbang",
  "bentukTidakBaku": "",
  "kataTurunan": [],
  "gabunganKata": [],
  "peribahasa": [],
  "etimologi": {
    "bahasaAsal": "",
    "arti": "",
    "kataAsal": ""
  },
  "data": [
    {
      "lema": "suara » suara sumbang",
      "arti": [
        {
          "kelas_kata": "",
          "deskripsi": "suara yang tidak sedap didengar"
        },
        {
          "kelas_kata": "ki[kiasan]",
          "deskripsi": "suara yang bernada bermusuhan"
        }
      ]
    }
  ]
}