{
  "istilah": "ultramikron",
  "entri": "ul.tra.mik.ron",
  "bentukTidakBaku": "",
  "kataTurunan": [],
  "gabunganKata": [],
  "peribahasa": [],
  "etimologi": {
    "bahasaAsal": "",
    "arti": "",
    "kataAsal": ""
  },
  "data": [
    {
      "lema": "ul.tra.mik.ron",
      "arti": [
        {
          "kelas_kata": "n[Nomina: kata benda] Kim[Kimia: -]",
          "deskripsi": "partikel yang berdiameter lebih kecil dari 0,25 mikron dan merupakan partikel terkecil yang dapat dilihat dengan ultramikroskop"
        }
      ]
    }
  ]
}