{
  "istilah": "berkecimpung",
  "entri": "kecimpung » ber.ke.cim.pung",
  "bentukTidakBaku": "",
  "kataTurunan": [],
  "gabunganKata": [],
  "peribahasa": [],
  "etimologi": {
    "bahasaAsal": "",
    "arti": "",
    "kataAsal": ""
  },
  "data": [
    {
      "lema": "kecimpung » ber.ke.cim.pung",
      "arti": [
        {
          "kelas_kata": "v[Verba: kata kerja]",
          "deskripsi": "bermain air dengan menepuk-nepuk air atau memukul-mukulkan kaki ke air sehingga berbunyi “pung, pung” (pada waktu mandi)"
        },
        {
          "kelas_kata": "v[Verba: kata kerja]",
          "deskripsi": "berbunyi “pung, pung” seperti air ditepuk"
        },
        {
          "kelas_kata": "v[Verba: kata kerja] ki[kiasan]",
          "deskripsi": "bergerak (dalam); berurusan (dalam): orang yang ~ dalam bidang pendidikan harus bersikap dinamis dan jujur"
        }
      ]
    }
  ]
}