{
  "istilah": "buhul",
  "entri": "bu.hul bentuk tidak baku: buhur",
  "bentukTidakBaku": "buhur",
  "kataTurunan": [
    "buhulan",
    "membuhul"
  ],
  "gabunganKata": [
    "buhul mati"
  ],
  "peribahasa": [],
  "etimologi": {
    "bahasaAsal": "",
    "arti": "",
    "kataAsal": ""
  },
  "data": [
    {
      "lema": "bu.hul bentuk tidak baku: buhur",
      "arti": [
        {
          "kelas_kata": "n[Nomina: kata benda]",
          "deskripsi": "simpul (tentang dasi)"
        }
      ]
    }
  ]
}