{
  "istilah": "gelegata",
  "entri": "ge.le.ga.ta /gêlêgata/",
  "bentukTidakBaku": "",
  "kataTurunan": [],
  "gabunganKata": [],
  "peribahasa": [],
  "etimologi": {
    "bahasaAsal": "",
    "arti": "",
    "kataAsal": ""
  },
  "data": [
    {
      "lema": "ge.le.ga.ta /gêlêgata/",
      "arti": [
        {
          "kelas_kata": "n[Nomina: kata benda]",
          "deskripsi": "penyakit kulit yang menimbulkan rasa sangat gatal (terutama di sela-sela jari kaki); bidur"
        },
        {
          "kelas_kata": "n[Nomina: kata benda]",
          "deskripsi": "bintil-bintil pada kulit (badan) karena kena jelatang, ulat bulu, dan sebagainya"
        },
        {
          "kelas_kata": "n[Nomina: kata benda]",
          "deskripsi": "kerut-kerut pada kulit (karena kedinginan dan sebagainya)"
        }
      ]
    }
  ]
}