{
  "istilah": "gelonggongan",
  "entri": "ge.long.go.ngan /gêlonggongan/",
  "bentukTidakBaku": "",
  "kataTurunan": [],
  "gabunganKata": [],
  "peribahasa": [],
  "etimologi": {
    "bahasaAsal": "",
    "arti": "",
    "kataAsal": ""
  },
  "data": [
    {
      "lema": "ge.long.go.ngan /gêlonggongan/",
      "arti": [
        {
          "kelas_kata": "n[Nomina: kata benda] Jw[Jawa: -]",
          "deskripsi": "daging yang berasal dari hewan potong yang sebelum penyembelihan diberi minum dengan slang secara paksa dalam jumlah besar, bertujuan untuk meningkatkan massa atau bobot daging sehingga harga jualnya lebih tinggi"
        }
      ]
    }
  ]
}