{
  "istilah": "gumbak cadek",
  "entri": "Gum.bak Ca.dek",
  "bentukTidakBaku": "",
  "kataTurunan": [],
  "gabunganKata": [],
  "peribahasa": [],
  "etimologi": {
    "bahasaAsal": "",
    "arti": "",
    "kataAsal": ""
  },
  "data": [
    {
      "lema": "Gum.bak Ca.dek",
      "arti": [
        {
          "kelas_kata": "n[Nomina: kata benda]",
          "deskripsi": "suku bangsa yang mendiami wilayah pedalaman Aceh Barat"
        },
        {
          "kelas_kata": "n[Nomina: kata benda]",
          "deskripsi": "bahasa yang dituturkan oleh suku Gumbak Cadek"
        }
      ]
    }
  ]
}