{
  "istilah": "ekses",
  "entri": "ek.ses",
  "bentukTidakBaku": "",
  "kataTurunan": [],
  "gabunganKata": [],
  "peribahasa": [],
  "etimologi": {
    "bahasaAsal": "",
    "arti": "",
    "kataAsal": ""
  },
  "data": [
    {
      "lema": "ek.ses",
      "arti": [
        {
          "kelas_kata": "n[Nomina: kata benda]",
          "deskripsi": "hal (peristiwa) yang melampaui batas: peristiwa itu boleh dianggap sebagai -- keberpihakan petugas keamanan kepada salah satu pihak yang bertikai"
        }
      ]
    }
  ]
}