{
  "istilah": "enakan",
  "entri": "enak » e.nak.an",
  "bentukTidakBaku": "",
  "kataTurunan": [],
  "gabunganKata": [],
  "peribahasa": [],
  "etimologi": {
    "bahasaAsal": "",
    "arti": "",
    "kataAsal": ""
  },
  "data": [
    {
      "lema": "enak » e.nak.an",
      "arti": [
        {
          "kelas_kata": "a[Adjektiva: kata yang menjelaskan nomina atau pronomina] cak[Cakapan: menandai kata yang digunakan dalam ragam takbaku]",
          "deskripsi": "lebih enak: badannya ~ setelah berobat"
        }
      ]
    }
  ]
}