{
  "istilah": "obligasi tunda bunga",
  "entri": "obligasi » obligasi tunda bunga",
  "bentukTidakBaku": "",
  "kataTurunan": [],
  "gabunganKata": [],
  "peribahasa": [],
  "etimologi": {
    "bahasaAsal": "",
    "arti": "",
    "kataAsal": ""
  },
  "data": [
    {
      "lema": "obligasi » obligasi tunda bunga",
      "arti": [
        {
          "kelas_kata": "",
          "deskripsi": "obligasi yang suku bunganya naik secara bertahap hingga tingkat bunga tertentu atau yang pembayaran bunganya ditunda sampai kemampuan perusahaan memungkinkannya"
        }
      ]
    }
  ]
}