{
  "istilah": "nefridium",
  "entri": "nef.ri.di.um",
  "bentukTidakBaku": "",
  "kataTurunan": [],
  "gabunganKata": [],
  "peribahasa": [],
  "etimologi": {
    "bahasaAsal": "",
    "arti": "",
    "kataAsal": ""
  },
  "data": [
    {
      "lema": "nef.ri.di.um",
      "arti": [
        {
          "kelas_kata": "n[Nomina: kata benda]",
          "deskripsi": "saluran ginjal, lazim terdapat pada dunia hewan, berfungsi sebagai anggota tubuh guna pembuangan zat yang mengandung zat lemas"
        }
      ]
    }
  ]
}