{
  "istilah": "nulipara",
  "entri": "nu.li.pa.ra",
  "bentukTidakBaku": "",
  "kataTurunan": [],
  "gabunganKata": [],
  "peribahasa": [],
  "etimologi": {
    "bahasaAsal": "",
    "arti": "",
    "kataAsal": ""
  },
  "data": [
    {
      "lema": "nu.li.pa.ra",
      "arti": [
        {
          "kelas_kata": "n[Nomina: kata benda] Dok[Kedokteran dan Fisiologi: -]",
          "deskripsi": "wanita yang belum pernah melahirkan atau pernah melahirkan tetapi bayinya meninggal"
        }
      ]
    }
  ]
}