{
  "istilah": "nyanyian rohani",
  "entri": "nyanyi » nyanyian » nyanyian rohani",
  "bentukTidakBaku": "",
  "kataTurunan": [],
  "gabunganKata": [],
  "peribahasa": [],
  "etimologi": {
    "bahasaAsal": "",
    "arti": "",
    "kataAsal": ""
  },
  "data": [
    {
      "lema": "nyanyi » nyanyian » nyanyian rohani",
      "arti": [
        {
          "kelas_kata": "",
          "deskripsi": "nyanyian yang melodi dan syairnya dibuat untuk mendekatkan diri pada Tuhan"
        }
      ]
    }
  ]
}