{
  "istilah": "vikuna",
  "entri": "vi.ku.na",
  "bentukTidakBaku": "",
  "kataTurunan": [],
  "gabunganKata": [],
  "peribahasa": [],
  "etimologi": {
    "bahasaAsal": "",
    "arti": "",
    "kataAsal": ""
  },
  "data": [
    {
      "lema": "vi.ku.na",
      "arti": [
        {
          "kelas_kata": "n[Nomina: kata benda]",
          "deskripsi": "mamalia berleher panjang, hidup di Pegunungan Andes yang memanjang dari Peru ke Argentina, warna bulunya cokelat muda, banyak diburu karena bulu dan dagingnya, dianggap merupakan moyang dari alpaka〔Vicugna vicugna〕 atau 〔Lama vicugna〕"
        },
        {
          "kelas_kata": "n[Nomina: kata benda] Tbs[Tata Busana: -]",
          "deskripsi": "kain dengan permukaan yang sangat lembut, terbuat dari bulu bagian bawah tubuh hewan vikuna"
        }
      ]
    }
  ]
}